examples/__init__.py
examples/base.py
newswacafi/__init__.py
newswacafi/api.py
newswacafi/response.py
newswacafi-0.6.dist-info/METADATA
newswacafi-0.6.dist-info/WHEEL
newswacafi-0.6.dist-info/top_level.txt
newswacafi-0.6.dist-info/RECORD
