Metadata-Version: 2.1
Name: newswacafi
Version: 0.6
Summary: Une bibliothèque Python pour interagir avec l'API de Newswacafi.
Home-page: https://newswacafi.online
Author: DRC WANALA
Author-email: contact@newswacafi.online
License: MIT
Classifier: Programming Language :: Python :: 3
Classifier: License :: OSI Approved :: MIT License
Classifier: Operating System :: OS Independent
Requires-Python: >=3.11.7
Requires-Dist: requests
